restkiss/__init__.py
restkiss/constants.py
restkiss/data.py
restkiss/dj.py
restkiss/exceptions.py
restkiss/fl.py
restkiss/it.py
restkiss/preparers.py
restkiss/pyr.py
restkiss/resources.py
restkiss/serializers.py
restkiss/tnd.py
restkiss/utils.py
restless/__init__.py
restless/constants.py
restless/data.py
restless/dj.py
restless/exceptions.py
restless/fl.py
restless/it.py
restless/preparers.py
restless/pyr.py
restless/resources.py
restless/serializers.py
restless/tnd.py
restless/utils.py
restless-2.0.2.dist-info/DESCRIPTION.rst
restless-2.0.2.dist-info/METADATA
restless-2.0.2.dist-info/RECORD
restless-2.0.2.dist-info/WHEEL
restless-2.0.2.dist-info/metadata.json
restless-2.0.2.dist-info/top_level.txt
