Metadata-Version: 2.0
Name: restless
Version: 2.0.2
Summary: A lightweight REST miniframework for Python.
Home-page: http://github.com/toastdriven/restless/
Author: Daniel Lindsley
Author-email: daniel@toastdriven.com
License: UNKNOWN
Platform: UNKNOWN
Classifier: Development Status :: 5 - Production/Stable
Classifier: Environment :: Web Environment
Classifier: Framework :: Django
Classifier: Framework :: Flask
Classifier: Framework :: Pyramid
Classifier: Intended Audience :: Developers
Classifier: License :: OSI Approved :: BSD License
Classifier: Operating System :: OS Independent
Classifier: Programming Language :: Python
Classifier: Programming Language :: Python :: 2
Classifier: Programming Language :: Python :: 3
Classifier: Topic :: Utilities
Requires: six(>=1.4.0)
Requires-Dist: six (>=1.4.0)
